map_utils_xethhung12/DensoMapCode.py
map_utils_xethhung12/GoogleMap.py
map_utils_xethhung12/GridSystem.py
map_utils_xethhung12/__init__.py
map_utils_xethhung12-0.5.0.dist-info/licenses/LICENSE
map_utils_xethhung12-0.5.0.dist-info/METADATA
map_utils_xethhung12-0.5.0.dist-info/WHEEL
map_utils_xethhung12-0.5.0.dist-info/top_level.txt
map_utils_xethhung12-0.5.0.dist-info/RECORD
