Metadata-Version: 2.4
Name: map-utils-xethhung12
Version: 0.5.0
Summary: A small package with maps related utils
Author-email: Xeth Hung <admin@xethh.me>
Project-URL: Homepage, https://github.com/xh-dev-py/map-utils-xethhung12
Project-URL: Issues, https://github.com/xh-dev-py/map-utils-xethhung12/issues
Classifier: Programming Language :: Python :: 3
Classifier: License :: OSI Approved :: MIT License
Classifier: Operating System :: OS Independent
Requires-Python: >=3.8
License-File: LICENSE
Requires-Dist: requests
Requires-Dist: beautifulsoup4
Requires-Dist: pyjsparser
Requires-Dist: pyyaml
Requires-Dist: tzdata
Dynamic: license-file
